SIESTAstepper/__init__.py
SIESTAstepper/__main__.py
SIESTAstepper/core.py
SIESTAstepper/helpers.py
SIESTAstepper-2.1.0.dist-info/LICENSE
SIESTAstepper-2.1.0.dist-info/METADATA
SIESTAstepper-2.1.0.dist-info/WHEEL
SIESTAstepper-2.1.0.dist-info/top_level.txt
SIESTAstepper-2.1.0.dist-info/RECORD
